{
  "version": "tree-0.1",
  "tree": {
    "id": "App",
    "path": "",
    "children": {
      "Tree": {
        "id": "Tree",
        "path": "Tree",
        "constructInfo": {
          "fqn": "constructs.Construct",
          "version": "10.2.69"
        }
      },
      "zbrbora-AcademyS3Stack": {
        "id": "zbrbora-AcademyS3Stack",
        "path": "zbrbora-AcademyS3Stack",
        "children": {
          "zbrbora-academy-cdk-1": {
            "id": "zbrbora-academy-cdk-1",
            "path": "zbrbora-AcademyS3Stack/zbrbora-academy-cdk-1",
            "children": {
              "Resource": {
                "id": "Resource",
                "path": "zbrbora-AcademyS3Stack/zbrbora-academy-cdk-1/Resource",
                "attributes": {
                  "aws:cdk:cloudformation:type": "AWS::S3::Bucket",
                  "aws:cdk:cloudformation:props": {
                    "bucketName": "zbrbora-academy-cdk-1"
                  }
                },
                "constructInfo": {
                  "fqn": "aws-cdk-lib.aws_s3.CfnBucket",
                  "version": "2.22.0"
                }
              }
            },
            "constructInfo": {
              "fqn": "aws-cdk-lib.aws_s3.Bucket",
              "version": "2.22.0"
            }
          },
          "zbrbora-academy-cdk-2": {
            "id": "zbrbora-academy-cdk-2",
            "path": "zbrbora-AcademyS3Stack/zbrbora-academy-cdk-2",
            "children": {
              "Resource": {
                "id": "Resource",
                "path": "zbrbora-AcademyS3Stack/zbrbora-academy-cdk-2/Resource",
                "attributes": {
                  "aws:cdk:cloudformation:type": "AWS::S3::Bucket",
                  "aws:cdk:cloudformation:props": {
                    "bucketName": "zbrbora-academy-cdk-2"
                  }
                },
                "constructInfo": {
                  "fqn": "aws-cdk-lib.aws_s3.CfnBucket",
                  "version": "2.22.0"
                }
              }
            },
            "constructInfo": {
              "fqn": "aws-cdk-lib.aws_s3.Bucket",
              "version": "2.22.0"
            }
          },
          "zbrbora-academy-cdk-3": {
            "id": "zbrbora-academy-cdk-3",
            "path": "zbrbora-AcademyS3Stack/zbrbora-academy-cdk-3",
            "children": {
              "Resource": {
                "id": "Resource",
                "path": "zbrbora-AcademyS3Stack/zbrbora-academy-cdk-3/Resource",
                "attributes": {
                  "aws:cdk:cloudformation:type": "AWS::S3::Bucket",
                  "aws:cdk:cloudformation:props": {
                    "bucketName": "zbrbora-academy-cdk-3"
                  }
                },
                "constructInfo": {
                  "fqn": "aws-cdk-lib.aws_s3.CfnBucket",
                  "version": "2.22.0"
                }
              }
            },
            "constructInfo": {
              "fqn": "aws-cdk-lib.aws_s3.Bucket",
              "version": "2.22.0"
            }
          },
          "zbrbora-academy-cdk-4": {
            "id": "zbrbora-academy-cdk-4",
            "path": "zbrbora-AcademyS3Stack/zbrbora-academy-cdk-4",
            "children": {
              "Resource": {
                "id": "Resource",
                "path": "zbrbora-AcademyS3Stack/zbrbora-academy-cdk-4/Resource",
                "attributes": {
                  "aws:cdk:cloudformation:type": "AWS::S3::Bucket",
                  "aws:cdk:cloudformation:props": {
                    "bucketName": "zbrbora-academy-cdk-4"
                  }
                },
                "constructInfo": {
                  "fqn": "aws-cdk-lib.aws_s3.CfnBucket",
                  "version": "2.22.0"
                }
              }
            },
            "constructInfo": {
              "fqn": "aws-cdk-lib.aws_s3.Bucket",
              "version": "2.22.0"
            }
          },
          "zbrbora-academy-cdk-5": {
            "id": "zbrbora-academy-cdk-5",
            "path": "zbrbora-AcademyS3Stack/zbrbora-academy-cdk-5",
            "children": {
              "Resource": {
                "id": "Resource",
                "path": "zbrbora-AcademyS3Stack/zbrbora-academy-cdk-5/Resource",
                "attributes": {
                  "aws:cdk:cloudformation:type": "AWS::S3::Bucket",
                  "aws:cdk:cloudformation:props": {
                    "bucketName": "zbrbora-academy-cdk-5"
                  }
                },
                "constructInfo": {
                  "fqn": "aws-cdk-lib.aws_s3.CfnBucket",
                  "version": "2.22.0"
                }
              }
            },
            "constructInfo": {
              "fqn": "aws-cdk-lib.aws_s3.Bucket",
              "version": "2.22.0"
            }
          },
          "CDKMetadata": {
            "id": "CDKMetadata",
            "path": "zbrbora-AcademyS3Stack/CDKMetadata",
            "children": {
              "Default": {
                "id": "Default",
                "path": "zbrbora-AcademyS3Stack/CDKMetadata/Default",
                "constructInfo": {
                  "fqn": "aws-cdk-lib.CfnResource",
                  "version": "2.22.0"
                }
              }
            },
            "constructInfo": {
              "fqn": "constructs.Construct",
              "version": "10.2.69"
            }
          }
        },
        "constructInfo": {
          "fqn": "aws-cdk-lib.Stack",
          "version": "2.22.0"
        }
      }
    },
    "constructInfo": {
      "fqn": "aws-cdk-lib.App",
      "version": "2.22.0"
    }
  }
}